crf_tagger/__init__.py
crf_tagger/_fileresource.py
crf_tagger/compat.py
crf_tagger/estimator.py
crf_tagger/metrics.py
crf_tagger/scorers.py
crf_tagger/trainer.py
crf_tagger/utils.py
crf_tagger-0.3.1.dist-info/WHEEL
crf_tagger-0.3.1.dist-info/METADATA
crf_tagger-0.3.1.dist-info/RECORD
